{"Stops" : [{"StopId":20916,"StopCode":"BP5477","PointLetter":"T","StopName":"Coulsdon South Station","Latitude":51.315612,"Longitude":-0.138573,"Action":0},{"StopId":6903,"StopCode":"20677","PointLetter":"G","StopName":"Coulsdon Library","Latitude":51.319659,"Longitude":-0.139156,"Action":0},{"StopId":7129,"StopCode":"4404","PointLetter":"J","StopName":"Coulsdon Town Station","Latitude":51.321600,"Longitude":-0.137384,"Action":0},{"StopId":4576,"StopCode":"BP4928","PointLetter":"R","StopName":"The Avenue","Latitude":51.322709,"Longitude":-0.137009,"Action":0},{"StopId":20412,"StopCode":"HC46","PointLetter":"","StopName":"Hail & Ride Section","Latitude":51.324128,"Longitude":-0.157906,"Action":0},{"StopId":4499,"StopCode":"BP813","PointLetter":"","StopName":"The Mount","Latitude":51.326401,"Longitude":-0.153739,"Action":0},{"StopId":20414,"StopCode":"HC47","PointLetter":"","StopName":"Hail & Ride Section","Latitude":51.321714,"Longitude":-0.142259,"Action":0},{"StopId":4460,"StopCode":"BP2140","PointLetter":"L","StopName":"Bramley Avenue","Latitude":51.322840,"Longitude":-0.140132,"Action":0},{"StopId":4071,"StopCode":"BP3305","PointLetter":"","StopName":"Warwick Road","Latitude":51.325745,"Longitude":-0.137905,"Action":0},{"StopId":5271,"StopCode":"BP1980","PointLetter":"","StopName":"Upper Woodcote Village","Latitude":51.333513,"Longitude":-0.139471,"Action":0},{"StopId":4454,"StopCode":"BP1981","PointLetter":"F","StopName":"Woodcote Park","Latitude":51.338779,"Longitude":-0.143737,"Action":0},{"StopId":10628,"StopCode":"17726","PointLetter":"V","StopName":"Farm Lane","Latitude":51.342536,"Longitude":-0.145883,"Action":0},{"StopId":10634,"StopCode":"16614","PointLetter":"W","StopName":"Lordsbury Field","Latitude":51.346178,"Longitude":-0.147028,"Action":0},{"StopId":8443,"StopCode":"16615","PointLetter":"X","StopName":"Woodcote Green","Latitude":51.348464,"Longitude":-0.148272,"Action":0},{"StopId":10018,"StopCode":"16617","PointLetter":"Y","StopName":"Hall Road","Latitude":51.350932,"Longitude":-0.147943,"Action":0},{"StopId":10030,"StopCode":"16619","PointLetter":"Z","StopName":"Blenheim Gardens","Latitude":51.353519,"Longitude":-0.148341,"Action":0},{"StopId":9987,"StopCode":"16621","PointLetter":"G","StopName":"Woodcote Road / Stafford Road","Latitude":51.356509,"Longitude":-0.149168,"Action":0},{"StopId":10019,"StopCode":"16623","PointLetter":"K","StopName":"Wallington Town Centre","Latitude":51.358956,"Longitude":-0.149773,"Action":0},{"StopId":13015,"StopCode":"36654","PointLetter":"D","StopName":"Wallington Station","Latitude":51.360685,"Longitude":-0.150551,"Action":0},{"StopId":9904,"StopCode":"17353","PointLetter":"GK","StopName":"Queens Road","Latitude":51.364183,"Longitude":-0.151646,"Action":0},{"StopId":8469,"StopCode":"36004","PointLetter":"GP","StopName":"Croydon Road / Wallington Green","Latitude":51.367585,"Longitude":-0.152988,"Action":0},{"StopId":8535,"StopCode":"14181","PointLetter":"GR","StopName":"The Holt","Latitude":51.369285,"Longitude":-0.146139,"Action":0},{"StopId":8300,"StopCode":"14186","PointLetter":"GS","StopName":"Church Road","Latitude":51.369861,"Longitude":-0.139952,"Action":0},{"StopId":8275,"StopCode":"14188","PointLetter":"D","StopName":"Guy Road","Latitude":51.369128,"Longitude":-0.134551,"Action":0},{"StopId":9887,"StopCode":"BP4243","PointLetter":"B","StopName":"Hilliers Lane","Latitude":51.370388,"Longitude":-0.132891,"Action":0},{"StopId":9958,"StopCode":"BP204","PointLetter":"C","StopName":"Beddington Village","Latitude":51.373805,"Longitude":-0.131775,"Action":0},{"StopId":9963,"StopCode":"BP067","PointLetter":"","StopName":"Beddington / Asda","Latitude":51.376488,"Longitude":-0.130847,"Action":0},{"StopId":9889,"StopCode":"BP1370","PointLetter":"","StopName":"Marlowe Way","Latitude":51.377942,"Longitude":-0.127296,"Action":0},{"StopId":10035,"StopCode":"BP1368","PointLetter":"","StopName":"Beddington Farm Road Sorting Office","Latitude":51.382018,"Longitude":-0.130219,"Action":0},{"StopId":20905,"StopCode":"BP5476","PointLetter":"C","StopName":"Therapia Lane Tram Stop","Latitude":51.386055,"Longitude":-0.131348,"Action":0},{"StopId":20909,"StopCode":"BP5474","PointLetter":"","StopName":"Therapia Lane Tram Depot","Latitude":51.386964,"Longitude":-0.134746,"Action":0},{"StopId":20908,"StopCode":"BP5472","PointLetter":"J","StopName":"Coomber Way / Beddington Lane","Latitude":51.386324,"Longitude":-0.139227,"Action":0},{"StopId":5263,"StopCode":"BP1717","PointLetter":"B","StopName":"Beddington Lane Tram Stop","Latitude":51.388135,"Longitude":-0.141123,"Action":0},{"StopId":20904,"StopCode":"BP5467","PointLetter":"","StopName":"Sherwood Park Road","Latitude":51.400744,"Longitude":-0.145729,"Action":0},{"StopId":20902,"StopCode":"BP5465","PointLetter":"","StopName":"Tamworth Park","Latitude":51.402562,"Longitude":-0.148661,"Action":0},{"StopId":20899,"StopCode":"BP5463","PointLetter":"","StopName":"Cedars Avenue","Latitude":51.404374,"Longitude":-0.151233,"Action":0},{"StopId":20906,"StopCode":"BP5461","PointLetter":"X","StopName":"Acacia Road","Latitude":51.406789,"Longitude":-0.153824,"Action":0},{"StopId":17229,"StopCode":"BP4598","PointLetter":"S","StopName":"Mitcham Eastfields Station","Latitude":51.408212,"Longitude":-0.154011,"Action":0},{"StopId":16847,"StopCode":"BP4599","PointLetter":"","StopName":"St Mark's C Of E Academy Playing Fields","Latitude":51.409232,"Longitude":-0.152533,"Action":0},{"StopId":4513,"StopCode":"BP4600","PointLetter":"","StopName":"Warminster Way","Latitude":51.410564,"Longitude":-0.147446,"Action":0},{"StopId":4598,"StopCode":"BP4601","PointLetter":"","StopName":"Ebenezer Walk","Latitude":51.410735,"Longitude":-0.145181,"Action":0},{"StopId":17228,"StopCode":"BP4602","PointLetter":"VC","StopName":"Meopham Road / Woodstock Way","Latitude":51.410008,"Longitude":-0.143586,"Action":0},{"StopId":7259,"StopCode":"12665","PointLetter":"VP","StopName":"Streatham Park Cemetery","Latitude":51.408476,"Longitude":-0.142181,"Action":0},{"StopId":7308,"StopCode":"25839","PointLetter":"VQ","StopName":"Rosemead Avenue","Latitude":51.405824,"Longitude":-0.138895,"Action":0},{"StopId":6864,"StopCode":"25836","PointLetter":"L","StopName":"Northborough Road","Latitude":51.403580,"Longitude":-0.136298,"Action":0},{"StopId":6804,"StopCode":"BP3494","PointLetter":"J","StopName":"Ivy Gardens","Latitude":51.401946,"Longitude":-0.134783,"Action":0},{"StopId":6865,"StopCode":"25834","PointLetter":"H","StopName":"Pollards Hill Library","Latitude":51.399937,"Longitude":-0.132277,"Action":0},{"StopId":20915,"StopCode":"BP5330","PointLetter":"","StopName":"Pollards Hill","Latitude":51.398982,"Longitude":-0.128218,"Action":0}], "Routes" : [{"Id":8399,"Route":"463","From":"Coulsdon South Station","Towards":"Pollards Hill","Run":"1","IsDay":1,"encodedLevels":"P?AD@C@@D?BAF?BD@DH??B@D?@BBA?E?B??B@D?BC@EJ@AFG?G@B@D?A?EA?DA?H@BAFBBD?AJABAD@AEB@@DACFBC?@CBAE@B@EB?AC@A?FE@C?@C?A@E?@CD@?E?C@J@?BAA@C@BAF@C@?B?@H@@C@C@FA@BAG@D@BE@B@CBCAC@@@F@@?D@B@C?DCJ@BEBAF?ACBH@@C?FACAG@A@?AC?@DBD?BG?C?D?@E@?EG@?CA?E@?CBJ?C?E?DACH@CBAE@B?AEA??CDAF?A@AB??B@P","encodedPoints":"moexHnaZYGq@YoCc@m@Fa@NYZUf@c@l@c@EeAEs@LiIZe@MoAg@yBeBq@w@cHsKm@vACL?`@@hIJ`CRrBTvAR|@|AjGlAlCnBjIJl@^nCFrABzAC`CUrJ?|ABhBLxA`@nDZlBvEfUzCfXz@lJeF`BIKmFsViBuJ{RhO{CqIoGcRV]h@]nBq@hDw@RQ^c@b@q@`AiB~CuG\\_AxDmJxAoFp@{CbBkIw@wDcAaEmAmC{B}G{BkAaF}EcEmC}@Y_B]sGs@{Ad@oEh@cBCyGj@gBh@iFvBiHbDmKzHeFhE]`@eFrEqH`CaEfB{GtE}B^kG|BqCd@qBVuD\\gCt@oBpAkGrBcB]}Fu@aBEu@D}LdBuGnA}KpBIJ[BQIaMzAqAReDlAX|@LHL?t@KHDFJ@LAPIHI?q@SSMc@uAa@Ni@LuEhA{Br@gFnBaItEaHhEGu@?i@Gk@sAmHq@}B{AsIUmBc@mE}BgSi@kGOyDJ{KLmE`@oFHm@fAuLH_BHuFCS[Uc@OqEcCwAmBmAqAuAg@o@MqBAcFd@mCHoLU_BHAsBEOb@IX@|Dr@ARGFID[Cg@UAs@}BIc@HCIYGYWEOG{AB{@O{A@KHSLIhBANGHUBWQeHsAoCSX[NaQdEmAv@iIzL}@r@eBEwEWcEg@_@w@{@YI\\KNiCnLwArJ{AjLFbBRtAlF~OCJOLIAMMWAIEk@NkIjEm@VyEjCqDnFiGjGiDtBeFrCaARm@CwFo@mCD_GPOE[SyCgCk@nBKVWd@aFqG]l@mBzEsCzG_DrEqBhD_D|FcDxDmD|DgEtEuEbE]@a@a@iFkG_CeGe@qA?uAKwGsEuPY_@d@qBbAyD`B_FtAwA~B{D@WRFxB@d@IZM^Wn@w@xB{DvAmCzCwFhJaLpCwCjQ{OAQ@KBMXWXoAPkAlAkLL_ApAmGh@gB","Color":"993333","hasRunTwo":1,"startPoint":{"Latitude":51.315274,"Longitude":-0.138640},"endPoint":{"Latitude":51.398807,"Longitude":-0.127905}}]}


