{"Stops" : [{"StopId":7708,"StopCode":"BP2061","PointLetter":"","StopName":"Toplocks Estate / Glade Lane","Latitude":51.503030,"Longitude":-0.364126,"Action":0},{"StopId":7709,"StopCode":"BP2060","PointLetter":"","StopName":"Mcnair Road","Latitude":51.501776,"Longitude":-0.363825,"Action":0},{"StopId":7565,"StopCode":"BP2065","PointLetter":"","StopName":"Gregory Road","Latitude":51.500228,"Longitude":-0.368880,"Action":0},{"StopId":7707,"StopCode":"BP2064","PointLetter":"","StopName":"Wylie Road","Latitude":51.501939,"Longitude":-0.369064,"Action":0},{"StopId":7586,"StopCode":"BP2063","PointLetter":"","StopName":"Havelock Estate","Latitude":51.501960,"Longitude":-0.371253,"Action":0},{"StopId":7845,"StopCode":"35155","PointLetter":"","StopName":"Hunt Road","Latitude":51.500293,"Longitude":-0.372969,"Action":0},{"StopId":7580,"StopCode":"BP3766","PointLetter":"K","StopName":"Havelock Road","Latitude":51.499469,"Longitude":-0.376442,"Action":0},{"StopId":5963,"StopCode":"16269","PointLetter":"A","StopName":"Norwood Gardens","Latitude":51.498576,"Longitude":-0.378865,"Action":0},{"StopId":5846,"StopCode":"8412","PointLetter":"C","StopName":"Adelaide Road","Latitude":51.499280,"Longitude":-0.382284,"Action":0},{"StopId":5457,"StopCode":"BP2545","PointLetter":"","StopName":"Montague Waye","Latitude":51.499990,"Longitude":-0.386826,"Action":0},{"StopId":7724,"StopCode":"C96","PointLetter":"","StopName":"Featherstone Road","Latitude":51.502404,"Longitude":-0.385170,"Action":0},{"StopId":5371,"StopCode":"19033","PointLetter":"L","StopName":"The Green","Latitude":51.502967,"Longitude":-0.380957,"Action":0},{"StopId":5318,"StopCode":"15963","PointLetter":"N","StopName":"Southall Station","Latitude":51.506030,"Longitude":-0.378788,"Action":0},{"StopId":5483,"StopCode":"15961","PointLetter":"P","StopName":"Park Avenue","Latitude":51.507579,"Longitude":-0.378286,"Action":0},{"StopId":4824,"StopCode":"7699","PointLetter":"N","StopName":"Southall Broadway","Latitude":51.510498,"Longitude":-0.376050,"Action":0},{"StopId":4644,"StopCode":"CW58","PointLetter":"E","StopName":"Southall Town Hall","Latitude":51.512173,"Longitude":-0.375616,"Action":0},{"StopId":4684,"StopCode":"15310","PointLetter":"C","StopName":"North Avenue","Latitude":51.514430,"Longitude":-0.375607,"Action":0},{"StopId":5681,"StopCode":"25206","PointLetter":"SC","StopName":"Carlyle Avenue","Latitude":51.516777,"Longitude":-0.375596,"Action":0},{"StopId":4744,"StopCode":"34861","PointLetter":"V","StopName":"Telford Road","Latitude":51.516076,"Longitude":-0.364624,"Action":0},{"StopId":7573,"StopCode":"BP028","PointLetter":"A","StopName":"Wallis Road","Latitude":51.517698,"Longitude":-0.362331,"Action":0},{"StopId":7558,"StopCode":"CW4","PointLetter":"B","StopName":"Golf Links Estate","Latitude":51.517994,"Longitude":-0.358415,"Action":0},{"StopId":7716,"StopCode":"CW3","PointLetter":"C","StopName":"Greenford Road","Latitude":51.517745,"Longitude":-0.356017,"Action":0},{"StopId":5441,"StopCode":"17107","PointLetter":"E","StopName":"Windmill Lane","Latitude":51.519966,"Longitude":-0.354740,"Action":0},{"StopId":5346,"StopCode":"17109","PointLetter":"U","StopName":"Greenford Depot","Latitude":51.524516,"Longitude":-0.353438,"Action":0},{"StopId":7753,"StopCode":"33862","PointLetter":"L","StopName":"Clifton Road","Latitude":51.527481,"Longitude":-0.350721,"Action":0},{"StopId":7458,"StopCode":"17025","PointLetter":"RS","StopName":"Greenford Avenue","Latitude":51.527393,"Longitude":-0.341916,"Action":0},{"StopId":7422,"StopCode":"17026","PointLetter":"RT","StopName":"Cuckoo Avenue","Latitude":51.527751,"Longitude":-0.338601,"Action":0},{"StopId":7362,"StopCode":"25078","PointLetter":"RW","StopName":"Gurnell Leisure Centre","Latitude":51.528649,"Longitude":-0.331519,"Action":0},{"StopId":7733,"StopCode":"37005","PointLetter":"B","StopName":"Perivale Lane","Latitude":51.533115,"Longitude":-0.330072,"Action":0},{"StopId":7392,"StopCode":"BP3467","PointLetter":"C","StopName":"Medway Parade","Latitude":51.534671,"Longitude":-0.333231,"Action":0},{"StopId":4620,"StopCode":"R0256","PointLetter":"E","StopName":"Teignmouth Gardens","Latitude":51.533920,"Longitude":-0.325328,"Action":0},{"StopId":4621,"StopCode":"R0222","PointLetter":"P","StopName":"Bideford Avenue","Latitude":51.533564,"Longitude":-0.322429,"Action":0},{"StopId":7474,"StopCode":"BP4879","PointLetter":"T","StopName":"Perivale Tesco","Latitude":51.534418,"Longitude":-0.319254,"Action":0}], "Routes" : [{"Id":5524,"Route":"E5","From":"Toplocks Estate / Glade Lane","Towards":"Perivale Tesco","Run":"1","IsDay":1,"encodedLevels":"P@C?F?A@?FA?DF@AE@B?C?AF@?B?FAFAAFBA@B?GA?A@@C?@BAB@CA@J@B??C@F?BA@CE@CBAGAAD?AB@F?C?I?FE?CAF?AAD@C@ABE?B@FACF?C?@BD?H?B?D@BH@ABCEA?B?BCA@CG?B?@?E?AACE@@@BA@F?@?@C@D@B@H?A@@CAE?AB?@C??BC?ED?D?A@?D@A@DBAP","encodedPoints":"}ejyHzdfA^c@zD_DNJJLb@jAhAbERjA|BhJl@jCX~BDhADlC_CAAoBWaGU_AY_@SEg@?UDWLUPWl@Cd@DjCFjM?\\SjE|AG`GJEvGN~JIfF`IXnB@JMH?JLBNETCDQ@K`@}@hBI`@C\\KfC]fD[pAmA|JOfE}@fNq@jE{AzFGDO?w@UOOmCsD]a@a@YyAi@CYEkCFgDP_BL_Iq@uB{@oAcDoDyD_BmBsAUk@SDwIkCuCiAsBsAoBiAsBkBcGoDaBy@MCi`@CsF]iGg@P_ETiJ~IrAFgBFa@NO`AQGa@@]Z}CT}GOe@Y]SKi@Ia@??a@\\mCbBiKtBkIPc@c@o@{AkD{HkF~@iGFs@CSGUOOq@ADeB`B}\\iDI}HU{AOcDa@iCg@uZmHiEmBFkANsJd@eFPeJImNc@wLSgC_AwQ?oCDwBYoHu@iJeB}NIqAYkTS}@Q_@MOOGOGIBWP[d@sCjFkCbDiDbCGEODoDFmBEQLa@A{B\\@TBPHNHZBv@EhCc@tHILWLe@Gw@WBIJCf@Dp@@HEVc@Ho@HaBBoBE_ICCKS?QBa@XcBPmBJmPRmEvA_UKuBmA_@cAWJq@@W?i@CUEGOK]@oASAEHWp@Ln@`@","Color":"993333","hasRunTwo":1,"startPoint":{"Latitude":51.503196,"Longitude":-0.364456},"endPoint":{"Latitude":51.534223,"Longitude":-0.319513}}]}


