{"Stops" : [{"StopId":17956,"StopCode":"BP3807","PointLetter":"U","StopName":"Kew Retail Park","Latitude":51.478859,"Longitude":-0.279967,"Action":0},{"StopId":17639,"StopCode":"BP3809","PointLetter":"V","StopName":"West Park Road","Latitude":51.476375,"Longitude":-0.281659,"Action":0},{"StopId":19698,"StopCode":"BP5281","PointLetter":"W","StopName":"Taylor Avenue","Latitude":51.474723,"Longitude":-0.279388,"Action":0},{"StopId":17640,"StopCode":"FW38","PointLetter":"E","StopName":"Courtlands Avenue","Latitude":51.473735,"Longitude":-0.277020,"Action":0},{"StopId":17638,"StopCode":"BP3808","PointLetter":"F","StopName":"Chalkers Corner","Latitude":51.470069,"Longitude":-0.276640,"Action":0},{"StopId":9032,"StopCode":"16246","PointLetter":"G","StopName":"Mortlake Road","Latitude":51.468739,"Longitude":-0.278547,"Action":0},{"StopId":9024,"StopCode":"BP396","PointLetter":"H","StopName":"Manor Grove","Latitude":51.467711,"Longitude":-0.283827,"Action":0},{"StopId":1800,"StopCode":"R0293","PointLetter":"SB","StopName":"Manor Circus","Latitude":51.466978,"Longitude":-0.290319,"Action":0},{"StopId":1852,"StopCode":"16241","PointLetter":"SK","StopName":"Sheendale Road","Latitude":51.466099,"Longitude":-0.292900,"Action":0},{"StopId":1906,"StopCode":"16240","PointLetter":"RR","StopName":"Richmond Circus","Latitude":51.465073,"Longitude":-0.297833,"Action":0},{"StopId":1796,"StopCode":"20703","PointLetter":"D","StopName":"Richmond Station","Latitude":51.463389,"Longitude":-0.301984,"Action":0},{"StopId":1820,"StopCode":"16351","PointLetter":"F","StopName":"The Quadrant","Latitude":51.461936,"Longitude":-0.302902,"Action":0},{"StopId":2262,"StopCode":"36782","PointLetter":"J","StopName":"Richmond Bus Station","Latitude":51.459101,"Longitude":-0.304561,"Action":0},{"StopId":4433,"StopCode":"15210","PointLetter":"A","StopName":"Cresswell Road","Latitude":51.456083,"Longitude":-0.309164,"Action":0},{"StopId":8081,"StopCode":"14886","PointLetter":"B","StopName":"Cambridge Park","Latitude":51.454537,"Longitude":-0.311726,"Action":0},{"StopId":8082,"StopCode":"15557","PointLetter":"C","StopName":"St Stephen's Church","Latitude":51.453020,"Longitude":-0.313192,"Action":0},{"StopId":8064,"StopCode":"15558","PointLetter":"D","StopName":"Marble Hill Park / Crown Road","Latitude":51.451687,"Longitude":-0.316782,"Action":0},{"StopId":13518,"StopCode":"BP5096","PointLetter":"E","StopName":"Orleans Park School","Latitude":51.450705,"Longitude":-0.320416,"Action":0},{"StopId":8071,"StopCode":"9391","PointLetter":"F","StopName":"Lebanon Court","Latitude":51.448910,"Longitude":-0.323792,"Action":0},{"StopId":17758,"StopCode":"BP3284","PointLetter":"K","StopName":"Twickenham / King Street","Latitude":51.445774,"Longitude":-0.329030,"Action":0},{"StopId":18024,"StopCode":"R0168","PointLetter":"SL","StopName":"Popes Grotto","Latitude":51.442310,"Longitude":-0.331373,"Action":0},{"StopId":17922,"StopCode":"BP282","PointLetter":"SQ","StopName":"Michelham Gardens","Latitude":51.439017,"Longitude":-0.332515,"Action":0},{"StopId":17728,"StopCode":"BP115","PointLetter":"ST","StopName":"Mallard Place","Latitude":51.436845,"Longitude":-0.330925,"Action":0},{"StopId":18009,"StopCode":"BP118","PointLetter":"SY","StopName":"Grove Gardens","Latitude":51.432542,"Longitude":-0.328722,"Action":0},{"StopId":17806,"StopCode":"BP117","PointLetter":"T","StopName":"Manor Road","Latitude":51.431034,"Longitude":-0.327008,"Action":0},{"StopId":17909,"StopCode":"BP202","PointLetter":"U","StopName":"Teddington Lock","Latitude":51.428580,"Longitude":-0.324537,"Action":0},{"StopId":3851,"StopCode":"20786","PointLetter":"Z","StopName":"Cambridge Road","Latitude":51.427272,"Longitude":-0.328684,"Action":0},{"StopId":3864,"StopCode":"27351","PointLetter":"D","StopName":"Teddington / Elmfield Avenue","Latitude":51.427141,"Longitude":-0.332084,"Action":0},{"StopId":3749,"StopCode":"19484","PointLetter":"F","StopName":"Broad Street","Latitude":51.425950,"Longitude":-0.336845,"Action":0},{"StopId":5999,"StopCode":"19485","PointLetter":"J","StopName":"Teddington Memorial Hospital","Latitude":51.426446,"Longitude":-0.340754,"Action":0},{"StopId":6057,"StopCode":"19487","PointLetter":"K","StopName":"National Physical Laboratory","Latitude":51.427037,"Longitude":-0.343782,"Action":0},{"StopId":5998,"StopCode":"19490","PointLetter":"","StopName":"Oxford Road","Latitude":51.428022,"Longitude":-0.349832,"Action":0},{"StopId":12813,"StopCode":"25919","PointLetter":"HH","StopName":"Wellington Road","Latitude":51.428893,"Longitude":-0.353627,"Action":0},{"StopId":5929,"StopCode":"6433","PointLetter":"HA","StopName":"Parkside","Latitude":51.428449,"Longitude":-0.354606,"Action":0},{"StopId":6035,"StopCode":"6398","PointLetter":"HB","StopName":"Cross Street","Latitude":51.426287,"Longitude":-0.356309,"Action":0},{"StopId":6084,"StopCode":"20524","PointLetter":"HC","StopName":"Holly Road","Latitude":51.424484,"Longitude":-0.357870,"Action":0},{"StopId":6121,"StopCode":"35828","PointLetter":"HD","StopName":"Park Place","Latitude":51.423063,"Longitude":-0.358539,"Action":0},{"StopId":15822,"StopCode":"6437","PointLetter":"","StopName":"Uxbridge Road","Latitude":51.421163,"Longitude":-0.358981,"Action":0},{"StopId":15802,"StopCode":"6439","PointLetter":"G","StopName":"Hampton Pool","Latitude":51.418463,"Longitude":-0.358805,"Action":0},{"StopId":15823,"StopCode":"6451","PointLetter":"M","StopName":"Park Close","Latitude":51.415885,"Longitude":-0.359027,"Action":0},{"StopId":5775,"StopCode":"R0152","PointLetter":"N","StopName":"Hampton Church","Latitude":51.414344,"Longitude":-0.360089,"Action":0},{"StopId":5839,"StopCode":"19587","PointLetter":"P","StopName":"Garrick Villa","Latitude":51.412548,"Longitude":-0.358959,"Action":0},{"StopId":5960,"StopCode":"19586","PointLetter":"","StopName":"St Albans Lodge","Latitude":51.411526,"Longitude":-0.355372,"Action":0},{"StopId":5801,"StopCode":"19584","PointLetter":"","StopName":"The Thames Riviera","Latitude":51.409556,"Longitude":-0.350195,"Action":0},{"StopId":5692,"StopCode":"1958","PointLetter":"","StopName":"Hampton Lodge","Latitude":51.408018,"Longitude":-0.346943,"Action":0},{"StopId":5691,"StopCode":"19580","PointLetter":"D","StopName":"Hampton Court Green / Cardinal Wolsey","Latitude":51.406159,"Longitude":-0.343358,"Action":0},{"StopId":4546,"StopCode":"14117","PointLetter":"F","StopName":"Hampton Court Palace","Latitude":51.404295,"Longitude":-0.341901,"Action":0},{"StopId":5937,"StopCode":"BP1385","PointLetter":"G","StopName":"Hampton Court Station","Latitude":51.402663,"Longitude":-0.342837,"Action":0}], "Routes" : [{"Id":9729,"Route":"R68","From":"Kew Retail Park","Towards":"Hampton Court Station","Run":"1","IsDay":1,"encodedLevels":"P@BA@DEA@AG?@E?ABG@AACB@HBAD?B??AE?A?A@@BBC?@?AH?BD@AF@BB?BA?F@?ACCDD?FA?F?BEBCAE@BAGB@A@E???C@D?C@C@AI@A?@CAE@AGAAB@B@DCABFAA@CB?A?C@I@E@BD@A@CB?GC??ACA?DBJ?C?BC@FA@CD?BB@@?EB@AB@I?D?CD@AAAB?B@@GAA@CBBP","encodedPoints":"qpeyHrpu@Jj@Tf@zA|B~@v@HPw@xCdA@PJlBb@lDd@d@O`Aa@`CqAbAyBj@wA~E_PzBoFd@AjARFLpF`AlLCNBf@\\nAtP|ArJx@xHLlCNbGCdBOvECrAF|ABXT`AFDFJD`@GRPfB|AvH`CpI\\|BrBbPlBfPFx@lA|H^v@t@pB`CjDVHzD~BhFzBHS@a@h@MRQpBiCXUJ?JFNx@J|BFl@j@|Bx@WvAjFkBhA@d@T~C~@]pCeBTQlIbQnErJ`CrHfAC`@j@`BbFZZZJ\\@rB]t@@zB|M~AzMPrBz@|ERn@b@fAf@`AzEbLjFnL~@tDnCpILRjBxBZBbA`@Hb@`@r@vCzD^Bb@PtAv@pHrD`Bp@nB~BtC|Bd@JrAJvFN~@e@fCeCvA}@jDgBt@SdEiCb@]pEgB|@K~CRz@_@dAcAf@_AlGaIRO~C_FJaAH]Zy@R[jBiBfBsAbAhBrDvHn@vI\\dIPfSJz@^vA^v@|AtFr@nFH|B?~AQdJIx@Qv@aBvKm@bGs@tHeA|RGn@aE|UeBtN|IjFbAr@pBjBfCjC`FrDr@`@lDvAlCj@fEp@pBTbGNjCIbAIvDcAtA?z@Gx@A\\BfBb@t@b@zBdBdHvDlATLAPMnCuCPwB`@yDhIg`@`BaFnDwJnFsMj@_CpDqJzCqG`CsEnAyD?QN]v@T|B|ARXdFhDd@]n@JLl@","Color":"993333","hasRunTwo":1,"startPoint":{"Latitude":51.479290,"Longitude":-0.279294},"endPoint":{"Latitude":51.402480,"Longitude":-0.343180}}]}


